LICENSE
MANIFEST.in
README.rst
fity3.py
setup.py
python_fity3.egg-info/PKG-INFO
python_fity3.egg-info/SOURCES.txt
python_fity3.egg-info/dependency_links.txt
python_fity3.egg-info/top_level.txt