Metadata-Version: 1.0
Name: python-fity3
Version: 0.7
Summary: Fity3 is a Twitter snowflake like scheme generator that fits in 53 bits.
Home-page: https://github.com/cablehead/python-fity3
Author: Andy Gayton
Author-email: andy@thecablelounge.com
License: MIT
Platform: UNKNOWN
